prepaynation_sdk/__init__.py
prepaynation_sdk/client.py
prepaynation_sdk-0.1.0.dist-info/METADATA
prepaynation_sdk-0.1.0.dist-info/WHEEL
prepaynation_sdk-0.1.0.dist-info/top_level.txt
prepaynation_sdk-0.1.0.dist-info/RECORD
