Metadata-Version: 2.4
Name: prepaynation_sdk
Version: 0.1.0
Summary: Python SDK for Prepay Nation Top‑Up API v2
Home-page: https://github.com/ninjaroot-509/prepaynation_sdk
Author: ninjaroot-509
Classifier: Programming Language :: Python :: 3
Classifier: License :: OSI Approved :: MIT License
Classifier: Operating System :: OS Independent
Requires-Python: >=3.6
Requires-Dist: requests>=2.20.0
Dynamic: author
Dynamic: classifier
Dynamic: description
Dynamic: description-content-type
Dynamic: home-page
Dynamic: requires-dist
Dynamic: requires-python
Dynamic: summary
